{
  "@type": "oa:Annotation",
  "@id": "/occupy/img/derivatives/iiif/annotation/OWS040.json",
  "motivation": "sc:painting",
  "resource": {
    "@id": "/occupy/img/derivatives/iiif/images/OWS040/full/full/0/default.jpg",
    "@type": "dcterms:Image",
    "format": "tiffload_source",
    "service": {
      "@context": "http://iiif.io/api/image/2/context.json",
      "@id": "/occupy/img/derivatives/iiif/images/OWS040",
      "profile": "http://iiif.io/api/image/2/level0.json"
    },
    "width": 5000,
    "height": 4872
  },
  "on": "/occupy/img/derivatives/iiif/canvas/OWS040.json",
  "@context": "http://iiif.io/api/presentation/2/context.json"
}
